airflow/providers/jira/__init__.py
airflow/providers/jira/get_provider_info.py
airflow/providers/jira/hooks/__init__.py
airflow/providers/jira/hooks/jira.py
airflow/providers/jira/operators/__init__.py
airflow/providers/jira/operators/jira.py
airflow/providers/jira/sensors/__init__.py
airflow/providers/jira/sensors/jira.py
apache_airflow_providers_jira-3.1.0.dist-info/LICENSE
apache_airflow_providers_jira-3.1.0.dist-info/METADATA
apache_airflow_providers_jira-3.1.0.dist-info/NOTICE
apache_airflow_providers_jira-3.1.0.dist-info/WHEEL
apache_airflow_providers_jira-3.1.0.dist-info/entry_points.txt
apache_airflow_providers_jira-3.1.0.dist-info/top_level.txt
apache_airflow_providers_jira-3.1.0.dist-info/RECORD
